LICENSE
MANIFEST.in
requirements.txt
setup.py
bin/pdns-dynamodb
pdns_dynamodb/__init__.py
pdns_dynamodb/app.py
pdns_dynamodb/backend.py
pdns_dynamodb/frontend.py
pdns_dynamodb.egg-info/PKG-INFO
pdns_dynamodb.egg-info/SOURCES.txt
pdns_dynamodb.egg-info/dependency_links.txt
pdns_dynamodb.egg-info/requires.txt
pdns_dynamodb.egg-info/top_level.txt
test/test_backend.py
test/test_frontend.py