Metadata-Version: 1.0
Name: pdns-dynamodb
Version: 1.0.1
Summary: PowerDNS backend using DynamoDB
Home-page: http://github.com/cosmin/pdns-dynamodb
Author: Cosmin Stejerean
Author-email: cosmin@offbytwo.com
License: Apache License 2.0
Platform: UNKNOWN
Classifier: Development Status :: 5 - Production/Stable
Classifier: Environment :: Console
Classifier: License :: OSI Approved :: Apache Software License
Classifier: Topic :: Utilities
